corptax/__init__.py
corptax/admin.py
corptax/app_settings.py
corptax/apps.py
corptax/auth_hooks.py
corptax/helpers.py
corptax/models.py
corptax/tasks.py
corptax/tax.py
corptax/urls.py
corptax/views.py
corptax/locale/.gitkeep
corptax/management/commands/__init__.py
corptax/management/commands/check_corp_registration.py
corptax/management/commands/discordbot-test.py
corptax/management/commands/expense-income.py
corptax/management/commands/fuel-calculator.py
corptax/management/commands/generate-praisel-moon.py
corptax/management/commands/generate_report.py
corptax/management/commands/model-test.old.py
corptax/management/commands/model-test.py
corptax/management/commands/moon_drill_value.py
corptax/management/commands/moon_rent.py
corptax/management/commands/notify-test.py
corptax/management/commands/personal_taxes.py
corptax/management/commands/spy-finder.py
corptax/management/commands/test-token.py
corptax/management/commands/test_discord.py
corptax/management/commands/test_view.py
corptax/migrations/0001_initial.py
corptax/migrations/0002_corpinvoice.py
corptax/migrations/0003_adminview.py
corptax/migrations/0004_invoice_moonledgermember.py
corptax/migrations/0005_moonledgermember_character_name.py
corptax/migrations/0006_corpstats.py
corptax/migrations/0007_alter_corpstats_corp_tax.py
corptax/migrations/0008_corpstats_corp_name_corpstats_total_member.py
corptax/migrations/0009_corpstats_alliance_id.py
corptax/migrations/0010_alliancefinance.py
corptax/migrations/0011_alter_alliancefinance_expense_and_more.py
corptax/migrations/0012_remove_alliancefinance_planatary_income.py
corptax/migrations/0013_alliancefinance_description.py
corptax/migrations/0014_troikavie_alter_adminview_options.py
corptax/migrations/0015_alter_corpinvoice_tax_reason.py
corptax/migrations/0015_discordnotification.py
corptax/migrations/0016_merge_20250505_1148.py
corptax/migrations/0017_delete_invoice_delete_taxpreview.py
corptax-0.1.9.6.dist-info/METADATA
corptax-0.1.9.6.dist-info/WHEEL
corptax-0.1.9.6.dist-info/licenses/LICENSE
corptax-0.1.9.6.dist-info/RECORD
