Metadata-Version: 2.4
Name: corptax
Version: 0.1.9.6
Summary: Moon and Ratting taxes based on corp usage
Project-URL: Changelog, https://git.ecdf.ed.ac.uk/jwinter/aa-corptax/-/blob/master/CHANGELOG.md?ref_type=heads
Project-URL: Issue / Bug Reports, https://git.ecdf.ed.ac.uk/jwinter/aa-corptax/-/issues
Author-email: Jan Winter <jan@mcwinter.org>
License-Expression: BSD-3-Clause
License-File: LICENSE
Keywords: allianceauth,corptax
Classifier: Environment :: Web Environment
Classifier: Framework :: Django
Classifier: Framework :: Django :: 4.2
Classifier: Intended Audience :: Developers
Classifier: Operating System :: OS Independent
Classifier: Programming Language :: Python
Classifier: Programming Language :: Python :: 3 :: Only
Classifier: Programming Language :: Python :: 3.10
Classifier: Programming Language :: Python :: 3.11
Classifier: Programming Language :: Python :: 3.12
Classifier: Topic :: Internet :: WWW/HTTP
Classifier: Topic :: Internet :: WWW/HTTP :: Dynamic Content
Requires-Python: >=3.10
Requires-Dist: aa-memberaudit>3
Requires-Dist: aa-moonmining>2
Requires-Dist: aa-structures>3
Requires-Dist: allianceauth-corptools>2.10
Requires-Dist: allianceauth-discordbot>4
Requires-Dist: allianceauth<5,>=4
